getreg.sv
module getreg();

  task convert;

    input [5:0] register;
    output [4*8:0] name;
    begin
      case(register)
        0: name = "zero";
        1: name = "ra";
        2: name = "sp";
        3: name = "gp";
        4: name = "tp";
        5: name = "t0";
        6: name = "t1";
        7: name = "t2";
        8: name = "s0fp";
        9: name = "s1";
       10: name = "a0";
       11: name = "a1";
       12: name = "a2";
       13: name = "a3";
       14: name = "a4";
       15: name = "a5";
       16: name = "a6";
       17: name = "a7";
       18: name = "s2";
       19: name = "s3";
       20: name = "s4";
       21: name = "s5";
       22: name = "s6";
       23: name = "s7";
       24: name = "s8";
       25: name = "s9";
       26: name = "s10";
       27: name = "s11";
       28: name = "t3";
       29: name = "t4";
       30: name = "t5";
       31: name = "t6";
      endcase
    end
  endtask
endmodule

decoder.sv
`include "getreg.sv"
module decoder();
getreg gr_name();

task decode;
input [31:0] lower;
input [63:0] pc;
logic [32:0] rd,rs1,rs2;
logic [64:0] opcode;
logic [7:0] sign;
logic signed [11:0] temp;
logic signed [12:0] temp_addr;
logic signed [64:0] address;
logic signed [64:0] pcint;
logic signed [20:0] offset;
begin
pcint = pc;
         if (lower[6:0] == 7'b0110011) begin
                gr_name.convert(lower[11:7],rd);
                gr_name.convert(lower[19:15],rs1);
                gr_name.convert(lower[24:20],rs2);
                case({lower[30], lower[25], lower[14:12]})
                        5'b00000: opcode = "add";
                        5'b10000: opcode = "sub";
                        5'b00001: opcode = "sll";
                        5'b00010: opcode = "slt";
                        5'b00110: opcode = "sltu";
                        5'b00100: opcode = "xor";
                        5'b10101: opcode = "sra";
                        5'b00101: opcode = "srl";
                        5'b00110: opcode = "or";
                        5'b00111: opcode = "and";
                        5'b01000: opcode = "mul";
                        5'b01001: opcode = "mulh";
                        5'b01010: opcode = "mulhsu";
                        5'b01011: opcode = "mulhu";
                        5'b01100: opcode = "div";
                        5'b01101: opcode = "divu";
                        5'b01110: opcode = "rem";
                        5'b01111: opcode = "remu";
                endcase
                $display ("%0x:  %x	%0s	%0s,%0s,%0s", pc, lower,opcode,rd,rs1,rs2);
        end else if (lower[6:0] == 7'b0010011) begin
                gr_name.convert(lower[11:7],rd);
                gr_name.convert(lower[19:15],rs1);
                temp = lower[31:20]; 
                case(lower[14:12])
                        3'b000: opcode = "addi";
                        3'b010: opcode = "slti";
                        3'b011: opcode = "sltiu";
                        3'b100: opcode = "xori";
                        3'b110: opcode = "ori";
                        3'b111: opcode = "andi";
                endcase
                case({lower[30], lower[14:12]})
                        4'b0001: opcode = "slli";
                        4'b0101: opcode = "srli";
                        4'b1101: opcode = "srai";
                endcase
                if (opcode == "addi") begin
                    if (temp == 0) begin
                       opcode = "mv";
                       if (rs1 == "zero") begin
                          if (rd == "zero") begin
                       $display("%0x:  %x	%0s", pc, lower,"nop");
                          end else
                       $display("%0x:  %x	%0s	%0s,0", pc, lower,"li",rd);
                       end else
                       $display("%0x:  %x	%0s	%0s,%0s", pc, lower,opcode,rd,rs1);
                    end else if (rs1 == "zero") begin
                       opcode = "li";
                       $display("%0x:  %x	%0s	%0s,%0d", pc, lower,opcode,rd,temp);
                     end else
                       $display("%0x:  %x	%0s	%0s,%0s,%0d", pc, lower,opcode,rd,rs1,temp);
                end  else
                       $display("%0x:  %x	%0s	%0s,%0s,%0d", pc, lower,opcode,rd,rs1,temp);

        end else if (lower[6:0] == 7'b1110011) begin
                gr_name.convert(lower[11:7],rd);
                gr_name.convert(lower[19:15],rs1);
                case (lower[14:12])
                        3'b001: $display("%x:	%x		csrrw         %s,%s",pc,lower,rd,rs1 );
                        3'b010: $display("%x:	%x		csrrs         %s,%s",pc,lower,rd,rs1);
                        3'b011: $display("%x:	%x		csrrc         %s,%s",pc,lower,rd,rs1);
                        3'b101: $display("%x:	%x		csrrwi        %s,%d",pc,lower,rd,lower[14:12]);
                        3'b110: $display("%x:	%x		csrrsi        %s,%d",pc,lower,rd,lower[14:12]);
                        3'b111: $display("%x:	%x		csrrci        %s,%d",pc,lower,rd,lower[14:12]);
                endcase
        end else if (lower[6:0] == 7'b0000011) begin
                gr_name.convert(lower[11:7],rd);
                gr_name.convert(lower[19:15],rs1);
                temp = lower[31:20];
                case (lower[14:12])
                        3'b000: opcode = "lb";
                        3'b001: opcode = "lh";
                        3'b010: opcode = "lw";
                        3'b100: opcode = "lbu";
                        3'b101: opcode = "lhu";
			3'b011: opcode = "ld";
			3'b110: opcode = "lwu";
                endcase
                $display ("%0x:  %x	%0s	%0s,%0d(%0s)", pc , lower,opcode,rd,temp,rs1);
        end else if (lower[6:0] == 7'b1100011) begin
                gr_name.convert(lower[24:20],rs2);
                gr_name.convert(lower[19:15],rs1);
                temp_addr = {lower[31],lower[7],lower[30:25],lower[11:8],1'b0}; 
                address = pcint + temp_addr;
                case (lower[14:12])
                        3'b000: opcode = "beq";
                        3'b001: opcode = "bne";
                        3'b100: opcode = "blt";
                        3'b101: opcode = "bge";
                        3'b110: opcode = "bltu";
                        3'b111: opcode = "bgeu";
               endcase
                $display ("%0x:  %x	%0s	%0s,%0s,0x%0x", pc , lower,opcode,rs1,rs2,address);
        end else if (lower[6:0]  == 7'b0100011) begin
                gr_name.convert(lower[19:15],rs1);
                gr_name.convert(lower[24:20],rs2);
                temp = {lower[31:25],lower[11:7]}; 
		case (lower[14:12])
                        3'b000: opcode = "sb";
                        3'b001: opcode = "sh";
                        3'b010: opcode = "sw";
                        3'b011: opcode = "sd";
                endcase
                $display ("%0x:  %x	%0s	%0s,%0d(%0s)", pc, lower,opcode,rs2,temp,rs1);

         end else if (lower[6:0] == 7'b0111011) begin
                gr_name.convert(lower[11:7],rd);
                gr_name.convert(lower[19:15],rs1);
                gr_name.convert(lower[24:20],rs2);
                case({lower[30],lower[25], lower[14:12]})
                        5'b00000: opcode = "addw";
                        5'b10000: opcode = "subw";
                        5'b00001: opcode = "sllw";
                        5'b00101: opcode = "srlw";
                        5'b10101: opcode = "sraw";
                        5'b01000: opcode = "mulw";
                        5'b01100: opcode = "divw";
                        5'b01101: opcode = "divwu";
                        5'b01110: opcode = "remw";
                        5'b01111: opcode = "remuw";
                endcase
                $display ("%0x:  %x	%0s	%0s,%0s,%0s", pc, lower,opcode,rd,rs1,rs2);
        end else if (lower[6:0] == 7'b0011011) begin
                gr_name.convert(lower[11:7],rd);
                gr_name.convert(lower[19:15],rs1);
                temp = lower[31:20]; 
                case(lower[14:12])
                        3'b000: opcode = "addiw";
                endcase
                case({lower[30], lower[14:12]})
                        4'b0001: opcode = "slliw";
                        4'b0101: opcode = "srliw";
                        4'b1101: opcode = "sraiw";
                endcase
                $display ("%0x:  %x	%0s	%0s,%0s,%0d", pc , lower,opcode,rd,rs1,temp);
        end else if (lower[6:0] == 7'b1110011) begin
                gr_name.convert(lower[11:7],rd);
                gr_name.convert(lower[19:15],rs1);
               case(lower[14:12])
                       3'b001: opcode = "csrrw";
                       3'b010: opcode = "csrrs";
                       3'b011: opcode = "csrrc";
               endcase
                $display ("%0x:	%x	%0s	%0s,csr,%0s", pc , lower,opcode,rd,rs1);
		       
        end else if (lower[6:0] == 7'b1110011) begin
                gr_name.convert(lower[11:7],rd);
               case(lower[14:12])
		       3'b001: opcode = "csrrw";
                       3'b001: opcode = "csrrw";
                       3'b001: opcode = "csrrw";
               endcase
                $display ("%0x:	%x	%0s	%0s,csr,%0d", pc , lower,opcode,rd,lower[19:15]);
        end else if (lower[31:0] == 32'b00000000000000000000000001110011) begin
		$display ("ecall");
        end else if (lower[31:0] == 32'b00000000000100000000000001110011) begin
		$display ("ebreak");
        end else if (lower[31:0] == 32'b00000000000000000001000000001111) begin
		$display ("fence.i");
        end else if (lower[31:0] == 32'b0000xxxxxxxx00000000000000001111) begin
		$display ("fence");
        end else if (lower[31:0] == 32'h00000000) begin
        end else begin
                case (lower[6:0])
                       7'b0110111: begin
                       gr_name.convert(lower[11:7],rd);
                       $display("%0x:  %x	%0s	%0s,0x%0x",pc,lower,"lui",rd,lower[31:12]);
                       end
                       7'b0010111:  begin
                       gr_name.convert(lower[11:7],rd);
                       $display("%0x:  %x	%0s	%0s,0x%0x",pc,lower,"auipc",rd,lower[31:12]);
                       end
                       7'b1101111: begin
                       gr_name.convert(lower[11:7],rd);
                       offset[20:0] = {lower[31],lower[19:12],lower[20],lower[30:21],1'b0};
                       address = pcint + offset;
                       $display ("%0x:  %x	%0s	%0s,0x%0x", pc , lower,"jal",rd,address);
                       end
                       7'b1100111: begin
                           gr_name.convert(lower[11:7],rd);
                           gr_name.convert(lower[19:15],rs1);
                           temp = lower[31:20];
                       $display ("%0x:  %x	%0s	%0s,%0s,%0d", pc , lower,"jalr",rd,rs1,temp);
                       end
                       default: $display("unknown at this time  ");
             endcase
        end
     end
    endtask
endmodule

top.sv
`include "Sysbus.defs"
`include "decoder.sv"
module top
#(
  BUS_DATA_WIDTH = 64,
  BUS_TAG_WIDTH = 13,
  UPPER_WIDTH = BUS_DATA_WIDTH >> 1
)
(
  input  clk,
         reset,

  // 64-bit address of the program entry point
  input  [63:0] entry,

  // interface to connect to the bus
  output bus_reqcyc,
  output bus_respack,
  output [BUS_DATA_WIDTH-1:0] bus_req,
  output [BUS_TAG_WIDTH-1:0] bus_reqtag,
  input  bus_respcyc,
  input  bus_reqack,
  input  [BUS_DATA_WIDTH-1:0] bus_resp,
  input  [BUS_TAG_WIDTH-1:0] bus_resptag
);
  decoder get_decoder();
 
 logic [64:0] opcode;
  logic [63:0] pc;
  logic [63:0] npc;
  logic out_of_reset;
  logic [3:0] data_index;
  logic [UPPER_WIDTH - 1:0] upper;
  logic [UPPER_WIDTH - 1:0] lower;
  enum {request=2'b10, waiting=2'b00, reading=2'b01} state, next_state;
  
  always_comb begin
  case (state)
	request: begin
		if ({bus_reqack,bus_respcyc} == 2'b10) begin
                      next_state = waiting;
		end
	end
	waiting: begin
		if ({bus_reqack,bus_respcyc} == 2'bx1) begin
			next_state = reading;
		end
	end
	reading: begin
		if ({bus_reqack,bus_respcyc} == 2'bx0) begin
			npc = pc + 8'h40;
			bus_req = npc;
			bus_reqtag = `SYSBUS_READ << 8 | `SYSBUS_MEMORY << 12;	
			next_state = request;
		end
	end
  endcase
  end

  always_ff @ (posedge clk) begin
	if (reset) begin
		pc <= entry;
	end else begin
		if (out_of_reset == 0) begin
			npc = pc;
    			bus_reqtag = `SYSBUS_READ << 8 | `SYSBUS_MEMORY << 12;
			out_of_reset = 1;
    			bus_respack <= 0;
    			bus_req = pc;
	         	bus_reqcyc <= 1;
			state <= request;
		end else begin
			if (next_state == reading) begin
        			lower = bus_resp[UPPER_WIDTH - 1:0];
        			upper = bus_resp[BUS_DATA_WIDTH-1:UPPER_WIDTH];
        			get_decoder.decode(lower, pc + data_index*4);
        			get_decoder.decode(upper, pc + (data_index + 1) * 4 );
        			if (upper == 32'h00000000) begin
          				$finish;
        			end
        			if (lower == 32'h00000000) begin
          				$finish;
        			end
				data_index <= data_index +2;
			end
			pc <=npc;
			state <=next_state;
			bus_reqcyc <= next_state[1];
			bus_respack <= next_state[0];
		end
	end
  end 

		
	


  initial begin
    $display("Initializing top, entry point = 0x%x", entry);
    data_index = 0;
    out_of_reset = 0;
  end
endmodule

trace.vcd
$version Generated by VerilatedVcd $end
$date Mon Feb  6 01:14:33 2017
 $end
$timescale   1ps $end

 $scope module TOP $end
  $var wire 64 3 bus_req [63:0] $end
  $var wire  1 7 bus_reqack $end
  $var wire  1 1 bus_reqcyc $end
  $var wire 13 5 bus_reqtag [12:0] $end
  $var wire 64 8 bus_resp [63:0] $end
  $var wire  1 2 bus_respack $end
  $var wire  1 6 bus_respcyc $end
  $var wire 13 : bus_resptag [12:0] $end
  $var wire  1 - clk $end
  $var wire 64 / entry [63:0] $end
  $var wire  1 . reset $end
  $scope module top $end
   $var wire 32 ; BUS_DATA_WIDTH [31:0] $end
   $var wire 32 < BUS_TAG_WIDTH [31:0] $end
   $var wire 32 = UPPER_WIDTH [31:0] $end
   $var wire 64 3 bus_req [63:0] $end
   $var wire  1 7 bus_reqack $end
   $var wire  1 1 bus_reqcyc $end
   $var wire 13 5 bus_reqtag [12:0] $end
   $var wire 64 8 bus_resp [63:0] $end
   $var wire  1 2 bus_respack $end
   $var wire  1 6 bus_respcyc $end
   $var wire 13 : bus_resptag [12:0] $end
   $var wire  1 - clk $end
   $var wire  4 $ data_index [3:0] $end
   $var wire 64 / entry [63:0] $end
   $var wire 32 + lower [31:0] $end
   $var wire 32 ' next_state [31:0] $end
   $var wire 64 % npc [63:0] $end
   $var wire 65 > opcode [64:0] $end
   $var wire  1 # out_of_reset $end
   $var wire 64 ( pc [63:0] $end
   $var wire  1 . reset $end
   $var wire 32 , state [31:0] $end
   $var wire 32 * upper [31:0] $end
  $upscope $end
 $upscope $end
$enddefinitions $end


#0
0#
b0000 $
b0000000000000000000000000000000000000000000000000000000000000000 %
b00000000000000000000000000000000 '
b0000000000000000000000000000000000000000000000000000000000000000 (
b00000000000000000000000000000000 *
b00000000000000000000000000000000 +
b00000000000000000000000000000000 ,
1-
1.
b0000000000000000000000000000000000000000000000000000000000000000 /
01
02
b0000000000000000000000000000000000000000000000000000000000000000 3
b0000000000000 5
06
07
b0000000000000000000000000000000000000000000000000000000000000000 8
b0000000000000 :
b00000000000000000000000001000000 ;
b00000000000000000000000000001101 <
b00000000000000000000000000100000 =
b00000000000000000000000000000000000000000000000000000000000000000 >
#125
b1010101010101010101010101010101010101010101010101010101010101010 8
b0101010101010 :
#250
0-
#375
#500
1-
#625
#750
0-
0.
#875
#1000
1#
b00000000000000000000000000000010 ,
1-
11
b1000100000000 5
#1125
#1250
0-
#1375
17
#1500
b00000000000000000000000000000000 ,
1-
01
#1625
07
#1750
0-
#1875
#2000
1-
#2125
#2250
0-
#2375
#2500
1-
#2625
#2750
0-
#2875
#3000
1-
#3125
#3250
0-
#3375
#3500
1-
#3625
#3750
0-
#3875
#4000
1-
#4125
#4250
0-
#4375
#4500
1-
#4625
#4750
0-
#4875
#5000
1-
#5125
#5250
0-
#5375
#5500
1-
#5625
#5750
0-
#5875
#6000
1-
#6125
#6250
0-
#6375
#6500
1-
#6625
#6750
0-
#6875
#7000
1-
#7125
#7250
0-
#7375
#7500
1-
#7625
#7750
0-
#7875
#8000
1-
#8125
#8250
0-
#8375
#8500
1-
#8625
#8750
0-
#8875
#9000
1-
#9125
#9250
0-
#9375
#9500
1-
#9625
#9750
0-
#9875
#10000
1-
#10125
#10250
0-
#10375
#10500
1-
#10625
#10750
0-
#10875
#11000
1-
#11125
#11250
0-
#11375
#11500
1-
#11625
#11750
0-
#11875
#12000
1-
#12125
#12250
0-
#12375
#12500
1-
#12625
#12750
0-
#12875
#13000
1-
#13125
#13250
0-
#13375
#13500
1-
#13625
#13750
0-
#13875
#14000
1-
#14125
#14250
0-
#14375
#14500
1-
#14625
#14750
0-
#14875
#15000
1-
#15125
#15250
0-
#15375
#15500
1-
#15625
#15750
0-
#15875
#16000
1-
#16125
#16250
0-
#16375
#16500
1-
#16625
#16750
0-
#16875
#17000
1-
#17125
#17250
0-
#17375
#17500
1-
#17625
#17750
0-
#17875
#18000
1-
#18125
#18250
0-
#18375
#18500
1-
#18625
#18750
0-
#18875
#19000
1-
#19125
#19250
0-
#19375
#19500
1-
#19625
#19750
0-
#19875
#20000
1-
#20125
#20250
0-
#20375
#20500
1-
#20625
#20750
0-
#20875
#21000
1-
#21125
#21250
0-
#21375
#21500
1-
#21625
#21750
0-
#21875
#22000
1-
#22125
#22250
0-
#22375
#22500
1-
#22625
#22750
0-
#22875
#23000
1-
#23125
#23250
0-
#23375
#23500
1-
#23625
#23750
0-
#23875
#24000
1-
#24125
#24250
0-
#24375
#24500
1-
#24625
#24750
0-
#24875
#25000
1-
#25125
#25250
0-
#25375
#25500
1-
#25625
#25750
0-
#25875
#26000
1-
#26125
#26250
0-
#26375
#26500
1-
#26625
#26750
0-
#26875
#27000
1-
#27125
#27250
0-
#27375
#27500
1-
#27625
#27750
0-
#27875
#28000
1-
#28125
#28250
0-
#28375
#28500
1-
#28625
#28750
0-
#28875
#29000
1-
#29125
#29250
0-
#29375
#29500
1-
#29625
#29750
0-
#29875
#30000
1-
#30125
#30250
0-
#30375
#30500
1-
#30625
#30750
0-
#30875
#31000
1-
#31125
#31250
0-
#31375
#31500
1-
#31625
#31750
0-
#31875
#32000
1-
#32125
#32250
0-
#32375
#32500
1-
#32625
#32750
0-
#32875
#33000
1-
#33125
#33250
0-
#33375
#33500
1-
#33625
#33750
0-
#33875
#34000
1-
#34125
#34250
0-
#34375
#34500
1-
#34625
#34750
0-
#34875
#35000
1-
#35125
#35250
0-
#35375
#35500
1-
#35625
#35750
0-
#35875
#36000
1-
#36125
#36250
0-
#36375
#36500
1-
#36625
#36750
0-
#36875
#37000
1-
#37125
#37250
0-
#37375
#37500
1-
#37625
#37750
0-
#37875
#38000
1-
#38125
#38250
0-
#38375
#38500
1-
#38625
#38750
0-
#38875
#39000
1-
#39125
#39250
0-
#39375
#39500
1-
#39625
#39750
0-
#39875
#40000
1-
#40125
#40250
0-
#40375
#40500
1-
#40625
#40750
0-
#40875
#41000
1-
#41125
#41250
0-
#41375
#41500
1-
#41625
#41750
0-
#41875
#42000
1-
#42125
#42250
0-
#42375
#42500
1-
#42625
#42750
0-
#42875
#43000
1-
#43125
#43250
0-
#43375
#43500
1-
#43625
#43750
0-
#43875
#44000
1-
#44125
#44250
0-
#44375
#44500
1-
#44625
#44750
0-
#44875
#45000
1-
#45125
#45250
0-
#45375
#45500
1-
#45625
#45750
0-
#45875
#46000
1-
#46125
#46250
0-
#46375
#46500
1-
#46625
#46750
0-
#46875
#47000
1-
#47125
#47250
0-
#47375
#47500
1-
#47625
#47750
0-
#47875
#48000
1-
#48125
b00000000000000000000000000000001 '
16
b0000001000010001001101000010001111111101000000010000000100010011 8
b1000100000000 :
#48250
0-
#48375
#48500
b0010 $
b00000010000100010011010000100011 *
b11111101000000010000000100010011 +
b00000000000000000000000000000001 ,
1-
12
#48625
b0000001100000001000001000001001100000010100000010011000000100011 8
#48750
0-
#48875
#49000
b0100 $
b00000011000000010000010000010011 *
b00000010100000010011000000100011 +
1-
#49125
b1111111010110100001000100010001111111110101001000011010000100011 8
#49250
0-
#49375
#49500
b0110 $
b11111110101101000010001000100011 *
b11111110101001000011010000100011 +
1-
#49625
b1111110110000100001101111000001111111100110001000011110000100011 8
#49750
0-
#49875
#50000
b1000 $
b11111101100001000011011110000011 *
b11111100110001000011110000100011 +
1-
#50125
b1111111111110111100001110001101100000000110001111010011110000011 8
#50250
0-
#50375
#50500
b1010 $
b11111111111101111000011100011011 *
b00000000110001111010011110000011 +
1-
#50625
b0000000011100111101001100010001111111101100001000011011110000011 8
#50750
0-
#50875
#51000
b1100 $
b00000000111001111010011000100011 *
b11111101100001000011011110000011 +
1-
#51125
b0000000011000111101001111000001111111101100001000011011110000011 8
#51250
0-
#51375
#51500
b1110 $
b00000000110001111010011110000011 *
1-
#51625
b1111110110000100001101111000001100000010000001111101010001100011 8
#51750
0-
#51875
#52000
b0000 $
b11111101100001000011011110000011 *
b00000010000001111101010001100011 +
1-
#52125
b0000000000000000000000000000000000000000000000000000000001000000 %
b00000000000000000000000000000010 '
b0000000000000000000000000000000000000000000000000000000001000000 3
06
b1010101010101010101010101010101010101010101010101010101010101010 8
b0101010101010 :
#52250
0-
#52375
#52500
b0000000000000000000000000000000000000000000000000000000001000000 (
b00000000000000000000000000000010 ,
1-
11
02
#52625
#52750
0-
#52875
b00000000000000000000000000000000 '
17
#53000
b00000000000000000000000000000000 ,
1-
01
#53125
07
